{
    "name": "python-jinja",
    "buildsystem": "simple",
    "build-commands": [
        "pip3 install --verbose --exists-action=i --no-index --find-links=\"file://${PWD}\" --prefix=${FLATPAK_DEST} \"Jinja2\" --no-build-isolation"
    ],
    "sources": [
        {
            "type": "file",
            "url": "https://files.pythonhosted.org/packages/f8/86/7c0eb6e8b05385d1ce682abc0f994abd1668e148fb52603fa86e15d4c110/Jinja2-3.0.2.tar.gz",
            "sha256": "827a0e32839ab1600d4eb1c4c33ec5a8edfbc5cb42dafa13b81f182f97784b45",
            "x-checker-data": {
                "type": "pypi",
                "name": "Jinja2"
            }
        }
    ],
    "modules": [
        "python-markupsafe/python-markupsafe.json"
    ]
}
